pykg2vec/__init__.py
pykg2vec/_version.py
pykg2vec/config/__init__.py
pykg2vec/config/config.py
pykg2vec/config/global_config.py
pykg2vec/config/hyperparams.py
pykg2vec/core/Complex.py
pykg2vec/core/ConvE.py
pykg2vec/core/ConvKB.py
pykg2vec/core/DistMult.py
pykg2vec/core/HoLE.py
pykg2vec/core/KG2E.py
pykg2vec/core/KGMeta.py
pykg2vec/core/NTN.py
pykg2vec/core/ProjE_pointwise.py
pykg2vec/core/Rescal.py
pykg2vec/core/RotatE.py
pykg2vec/core/SLM.py
pykg2vec/core/SME.py
pykg2vec/core/TransD.py
pykg2vec/core/TransE.py
pykg2vec/core/TransG.py
pykg2vec/core/TransH.py
pykg2vec/core/TransM.py
pykg2vec/core/TransR.py
pykg2vec/core/TuckER.py
pykg2vec/core/__init__.py
pykg2vec/test/__init__.py
pykg2vec/test/test_KGPipeline.py
pykg2vec/test/test_generator.py
pykg2vec/test/test_inference.py
pykg2vec/test/test_kg.py
pykg2vec/test/test_model.py
pykg2vec/test/test_tune_model.py
pykg2vec/utils/KGPipeline.py
pykg2vec/utils/__init__.py
pykg2vec/utils/bayesian_optimizer.py
pykg2vec/utils/evaluation.py
pykg2vec/utils/generator.py
pykg2vec/utils/kgcontroller.py
pykg2vec/utils/trainer.py
pykg2vec/utils/visualization.py
pykg2vec-0.0.50.dist-info/LICENSE
pykg2vec-0.0.50.dist-info/METADATA
pykg2vec-0.0.50.dist-info/WHEEL
pykg2vec-0.0.50.dist-info/top_level.txt
pykg2vec-0.0.50.dist-info/RECORD
