Metadata-Version: 2.1
Name: pykg2vec
Version: 0.0.50
Summary: A Python library for Knowledge Graph Embedding
Home-page: https://github.com/Sujit-O/pykg2vec.git
Author: Sujit Rokka Chhetri, Shih-Yuan Yu, Ahmet Salih Aksakal, Palash Goyal, Martinez Canedo, Arquimedes, Mohammad Abdullah Al Faruque
Author-email: sujitchhetri@gmail.com
License: UNKNOWN
Platform: UNKNOWN
Classifier: Programming Language :: Python :: 3.6
Classifier: License :: OSI Approved :: MIT License
Classifier: Operating System :: OS Independent
Requires-Dist: sphinx (>=2.1.2)
Requires-Dist: networkx (>=2.2)
Requires-Dist: setuptools (>=40.8.0)
Requires-Dist: tensorflow (<2,>=1.13.1)
Requires-Dist: matplotlib (>=3.0.3)
Requires-Dist: numpy (>=1.16.2)
Requires-Dist: seaborn (>=0.9.0)
Requires-Dist: scikit-learn (>=0.20.3)
Requires-Dist: hyperopt (>=0.2.1)
Requires-Dist: progressbar2 (>=3.39.3)
Requires-Dist: pathlib (>=1.0.1)
Requires-Dist: numpydoc (>=0.9.1)
Requires-Dist: sphinx-gallery (>=0.3.1)
Requires-Dist: sphinx-rtd-theme (>=0.4.3)
Requires-Dist: pytest (>=3.6)
